setup.py
PythonSudeste.egg-info/PKG-INFO
PythonSudeste.egg-info/SOURCES.txt
PythonSudeste.egg-info/dependency_links.txt
PythonSudeste.egg-info/top_level.txt
pyse/__init__.py