Metadata-Version: 1.1
Name: PythonSudeste
Version: 17.0.1
Summary: Everything you need to know about PythonSudeste
Home-page: https://github.com/etandel/pyse
Author: Elias Tandel
Author-email: elias.tandel@gmail.com
License: UNKNOWN
Download-URL: https://codeload.github.com/etandel/pyse/tar.gz/17.0.1
Platform: UNKNOWN
